Twitchvana/__init__.py
Twitchvana/bot.py
Twitchvana/channel.py
Twitchvana/command.py
Twitchvana/context.py
Twitchvana/errors.py
Twitchvana/irc_settings.py
Twitchvana/tsocket.py
Twitchvana/user_data_fetcher.py
Twitchvana/viewer.py
Twitchvana_AVANA-1.0.0.dist-info/LICENSE
Twitchvana_AVANA-1.0.0.dist-info/METADATA
Twitchvana_AVANA-1.0.0.dist-info/WHEEL
Twitchvana_AVANA-1.0.0.dist-info/top_level.txt
Twitchvana_AVANA-1.0.0.dist-info/RECORD
