Metadata-Version: 2.1
Name: Twitchvana-AVANA
Version: 1.0.0
Summary: Twitchvana for Twitch
Home-page: UNKNOWN
Author: Avana
Author-email: avana.artz@gmail.com
License: UNKNOWN
Platform: UNKNOWN
Classifier: Programming Language :: Python :: 3.7
Classifier: License :: OSI Approved :: MIT License
Classifier: Operating System :: OS Independent
Requires-Python: >=3.7.3
